fancy/sa/filemodel/__init__.py
fancy/sa/filemodel/file.py
fancy/sa/filemodel/file_model.py
fancy/sa/filemodel/operation.py
fancy/sa/filemodel/operation_context.py
fancy/sa/filemodel/storage.py
fancy/sa/filemodel/storage_manager.py
fancy_sa_filemodel-0.0.8.dist-info/LICENSE
fancy_sa_filemodel-0.0.8.dist-info/METADATA
fancy_sa_filemodel-0.0.8.dist-info/WHEEL
fancy_sa_filemodel-0.0.8.dist-info/top_level.txt
fancy_sa_filemodel-0.0.8.dist-info/RECORD
